{"cameraMode":{"drawMode":0,"name":"Shaded","section":"Shading Mode"},"sceneLighting":true,"audioPlay":false,"sceneViewState":{"showFog":true,"showMaterialUpdate":false,"showSkybox":true,"showFlares":true,"showImageEffects":true,"showParticleSystems":true},"in2DMode":false,"pivot":{"x":-1.517674207687378,"y":1.0833678245544434,"z":0.585026741027832},"rotation":{"x":-0.24204640090465547,"y":-0.05033242329955101,"z":0.012574542313814164,"w":-0.9688836336135864},"size":14.872586250305176,"orthographic":false}